toolbox_python/__init__.py
toolbox_python/bools.py
toolbox_python/checkers.py
toolbox_python/classes.py
toolbox_python/collection_types.py
toolbox_python/defaults.py
toolbox_python/dictionaries.py
toolbox_python/generators.py
toolbox_python/lists.py
toolbox_python/output.py
toolbox_python/retry.py
toolbox_python/strings.py
toolbox_python/validators.py
toolbox_python-1.5.0.dist-info/WHEEL
toolbox_python-1.5.0.dist-info/METADATA
toolbox_python-1.5.0.dist-info/RECORD
