Metadata-Version: 2.4
Name: toolbox-python
Version: 1.5.0
Summary: Helper files/functions/classes for generic Python processes
Author: Chris Mahoney
Author-email: Chris Mahoney <toolbox-python@data-science-extensions.com>
License-Expression: MIT
Classifier: Development Status :: 5 - Production/Stable
Classifier: License :: OSI Approved :: MIT License
Classifier: Topic :: Software Development :: Build Tools
Classifier: Topic :: Software Development :: Libraries :: Python Modules
Classifier: Topic :: Software Development :: Testing :: Unit
Classifier: Topic :: Utilities
Classifier: Programming Language :: Python :: 3
Classifier: Programming Language :: Python :: 3.9
Classifier: Programming Language :: Python :: 3.10
Classifier: Programming Language :: Python :: 3.11
Classifier: Programming Language :: Python :: 3.12
Classifier: Programming Language :: Python :: 3.13
Classifier: Intended Audience :: Developers
Requires-Dist: typeguard==4.*
Requires-Dist: more-itertools==10.*
Maintainer: Chris Mahoney
Maintainer-email: Chris Mahoney <toolbox-python@data-science-extensions.com>
Requires-Python: >=3.9
Project-URL: Changelog, https://github.com/data-science-extensions/toolbox-python/releases
Project-URL: Documentation, https://data-science-extensions.com/python-toolbox
Project-URL: Homepage, https://data-science-extensions.com/python-toolbox
Project-URL: Issues, https://github.com/data-science-extensions/toolbox-python/issues
Project-URL: Repository, https://github.com/data-science-extensions/toolbox-python
